fluent_http/__init__.py
fluent_http/exceptions.py
fluent_http/handler.py
fluent_http-0.1.0.dist-info/LICENSE
fluent_http-0.1.0.dist-info/METADATA
fluent_http-0.1.0.dist-info/WHEEL
fluent_http-0.1.0.dist-info/top_level.txt
fluent_http-0.1.0.dist-info/RECORD
