Metadata-Version: 2.1
Name: fluent-http
Version: 0.1.0
Summary: Fluentd logger client for HTTP input
Author-email: JM Robles <roblesjm@gmail.com>
License: Copyright 2022 JM Robles        
Keywords: fluent,fluentd,logging,handler,http
Classifier: License :: OSI Approved :: MIT License
Classifier: Programming Language :: Python
Classifier: Programming Language :: Python :: 3
Requires-Python: >=3.6
License-File: LICENSE
Requires-Dist: requests (>=2.0.0)
